{
  "variables": {
    "box_ostype":     "debian",
    "box_osversion":  "6.0.8",
    "box_nick":       "squeeze",
    "box_arch":       "x64",
    "box_type":       "base",
    "box_memory":     "256",
    "box_cpus":       "1",

    "ssh_user":       "vagrant",
    "ssh_pass":       "vagrant",
    "hostname":       "vagrant-debian-6.0.8",
    "domain":         "vagrantup.com"
  },

  "builders": [
    {
      "type":               "virtualbox-iso",
      "vm_name":            "{{ user `box_ostype` }}-{{ user `box_nick` }}-{{ user `box_arch` }}-{{ user `box_type` }}",
      "guest_os_type":      "Debian_64",
      "disk_size":          "5500",

      "iso_url":            "http://cdimage.debian.org/cdimage/archive/6.0.8/amd64/iso-cd/debian-6.0.8-amd64-netinst.iso",
      "iso_checksum":       "d675b89fa6b241e6e40783296a5bd92e",
      "iso_checksum_type":  "md5",

      "http_directory":     "http",

      "ssh_username":       "root",
      "ssh_password":       "{{ user `ssh_pass` }}",
      "ssh_wait_timeout":   "100000s",

      "shutdown_command":   "echo {{ user `ssh_user` }} | sudo halt -p",

      "vboxmanage": [
        [ "modifyvm", "{{ .Name }}", "--memory", "{{ user `box_memory` }}" ],
        [ "modifyvm", "{{ .Name }}", "--cpus",   "{{ user `box_cpus`   }}" ]
      ],

      "boot_command": [
        "<esc> ",
        "install ",
        "auto ",
        "preseed/url=http://{{ .HTTPIP }}:{{ .HTTPPort }}/preseed.cfg ",
        "debian-installer/locale=en_US ",
        "console-keymaps-at/keymap=en_US ",
        "console-setup/ask_detect=false ",
        "hostname={{ user `hostname` }} ",
        "domain={{ user `domain` }} ",
        "passwd/root-password={{ user `ssh_pass` }} ",
        "passwd/root-password-again={{ user `ssh_pass` }} ",
        "passwd/user-fullname={{ user `ssh_user` }} ",
        "passwd/username={{ user `ssh_user` }} ",
        "passwd/user-password={{ user `ssh_pass` }} ",
        "passwd/user-password-again={{ user `ssh_pass` }} ",
        "<enter><wait>"
      ]
    }
  ],

  "post-processors": [
    {
      "type":                 "vagrant",
      "output":               "{{ user `box_ostype` }}-{{ user `box_nick` }}-{{ user `box_arch` }}-{{ user `box_type` }}.box"
    }
  ],

  "provisioners": [
    {
      "execute_command": "echo 'root' | sh '{{ .Path }}'",
      "type": "shell",
      "override": {
        "virtualbox-iso": {
          "scripts": [
            "scripts/sudoers.sh",
            "scripts/sshd.sh",
            "scripts/virtualbox.sh",
            "scripts/vagrant.sh"
          ]
        }
      }
    }
  ]
}
